adg/__init__.py
adg/execute.py
appfire_data_genie-0.0.1.dist-info/METADATA
appfire_data_genie-0.0.1.dist-info/WHEEL
appfire_data_genie-0.0.1.dist-info/entry_points.txt
appfire_data_genie-0.0.1.dist-info/top_level.txt
appfire_data_genie-0.0.1.dist-info/RECORD
